document_detection/__init__.py
document_detection/detection.py
document_detection/node.py
document_detection/scope_table
document_detection/state_word.txt
document_detection/test.py
document_detection/utils.py
document_detection-1.0.4.dist-info/METADATA
document_detection-1.0.4.dist-info/WHEEL
document_detection-1.0.4.dist-info/top_level.txt
document_detection-1.0.4.dist-info/RECORD
